swiglpk.libs/libglpk-e7d58642.so.40.3.1
swiglpk.libs/libgmp-6683d5d4.so.10.2.0
swiglpk-5.0.12.dist-info/top_level.txt
swiglpk-5.0.12.dist-info/RECORD
swiglpk-5.0.12.dist-info/LICENSE
swiglpk-5.0.12.dist-info/METADATA
swiglpk-5.0.12.dist-info/WHEEL
swiglpk/__init__.py
swiglpk/swiglpk.py
swiglpk/_swiglpk.cpython-312-aarch64-linux-gnu.so
swiglpk/glpk.i
