Metadata-Version: 2.1
Name: swiglpk
Version: 5.0.12
Summary: swiglpk - Simple swig bindings for the GNU Linear Programming Kit
Home-page: https://github.com/biosustain/swiglpk
Author: Nikolaus Sonnenschein
Author-email: niko.sonnenschein@gmail.com
License: GPL v3
Keywords: optimization swig glpk
Classifier: Development Status :: 5 - Production/Stable
Classifier: Topic :: Scientific/Engineering
Classifier: Topic :: Software Development
Classifier: Intended Audience :: Science/Research
Classifier: Programming Language :: Python :: 2.7
Classifier: Programming Language :: Python :: 3.4
Classifier: License :: OSI Approved :: GNU General Public License v3 (GPLv3)
License-File: LICENSE
